{
  "type": "minecraft:block",
  "pools": [
    {
      "rolls": 1,
      "entries": [
        {
          "type": "minecraft:item",
          "name": "minecraft:cod",
          "weight": 10,
          "functions": [
            {
              "function": "set_count",
              "count": {
                "min": 1,
                "max": 1
              }
            }
          ]
        },
        {
          "type": "minecraft:item",
          "name": "minecraft:salmon",
          "weight": 10,
          "functions": [
            {
              "function": "set_count",
              "count": {
                "min": 1,
                "max": 1
              }
            }
          ]
        },
        {
          "type": "minecraft:item",
          "name": "minecraft:tropical_fish",
          "weight": 10,
          "functions": [
            {
              "function": "set_count",
              "count": {
                "min": 1,
                "max": 1
              }
            }
          ]
        },
        {
          "type": "minecraft:item",
          "name": "minecraft:pufferfish",
          "weight": 10,
          "functions": [
            {
              "function": "set_count",
              "count": {
                "min": 1,
                "max": 1
              }
            }
          ]
        },
        {
          "type": "minecraft:item",
          "name": "minecraft:glass_bottle",
          "weight": 10,
          "functions": [
            {
              "function": "set_count",
              "count": {
                "min": 1,
                "max": 1
              }
            }
          ]
        },
        {
          "type": "minecraft:item",
          "name": "minecraft:fishing_rod",
          "weight": 10,
          "functions": [
            {
              "function": "set_count",
              "count": {
                "min": 1,
                "max": 1
              }
            }
          ]
        },
        {
          "type": "minecraft:item",
          "name": "minecraft:air",
          "weight": 10,
          "functions": [
            {
              "function": "set_count",
              "count": {
                "min": 1,
                "max": 1
              }
            }
          ]
        },
        {
          "type": "minecraft:item",
          "name": "minecraft:stick",
          "weight": 5,
          "functions": [
            {
              "function": "set_count",
              "count": {
                "min": 1,
                "max": 1
              }
            }
          ]
        },
        {
          "type": "minecraft:item",
          "name": "minecraft:string",
          "weight": 5,
          "functions": [
            {
              "function": "set_count",
              "count": {
                "min": 1,
                "max": 1
              }
            }
          ]
        },
        {
          "type": "minecraft:item",
          "name": "minecraft:sand",
          "weight": 5,
          "functions": [
            {
              "function": "set_count",
              "count": {
                "min": 1,
                "max": 1
              }
            }
          ]
        },
        {
          "type": "minecraft:item",
          "name": "minecraft:clay_ball",
          "weight": 5,
          "functions": [
            {
              "function": "set_count",
              "count": {
                "min": 1,
                "max": 1
              }
            }
          ]
        },
        {
          "type": "minecraft:item",
          "name": "minecraft:glass",
          "weight": 5,
          "functions": [
            {
              "function": "set_count",
              "count": {
                "min": 1,
                "max": 1
              }
            }
          ]
        },
        {
          "type": "minecraft:item",
          "name": "morenugget:coal_nuggets",
          "weight": 1,
          "functions": [
            {
              "function": "set_count",
              "count": {
                "min": 1,
                "max": 1
              }
            }
          ]
        },
        {
          "type": "minecraft:item",
          "name": "minecraft:iron_nugget",
          "weight": 1,
          "functions": [
            {
              "function": "set_count",
              "count": {
                "min": 1,
                "max": 1
              }
            }
          ]
        },
        {
          "type": "minecraft:item",
          "name": "minecraft:gold_nugget",
          "weight": 1,
          "functions": [
            {
              "function": "set_count",
              "count": {
                "min": 1,
                "max": 1
              }
            }
          ]
        },
        {
          "type": "minecraft:item",
          "name": "morenugget:diamond_nuggets",
          "weight": 1,
          "functions": [
            {
              "function": "set_count",
              "count": {
                "min": 1,
                "max": 1
              }
            }
          ]
        },
        {
          "type": "minecraft:item",
          "name": "morenugget:emerald_nuggets",
          "weight": 1,
          "functions": [
            {
              "function": "set_count",
              "count": {
                "min": 1,
                "max": 1
              }
            }
          ]
        },
        {
          "type": "minecraft:item",
          "name": "minecraft:copper_nuggets",
          "weight": 10,
          "functions": [
            {
              "function": "set_count",
              "count": {
                "min": 1,
                "max": 1
              }
            }
          ]
        }
      ]
    }
  ]
}